{
  "resourceType": "Organization",
  "id": "va-org-visn6-cboc1",
  "text": {
    "status": "generated",
    "div": "<div xmlns='http://www.w3.org/1999/xhtml'>Virginia Beach CBOC</div>"
  },
  "active": true,
  "type": {
    "coding": [
      {
        "system": "http://hl7.org/fhir/organization-type",
        "code": "prov",
        "display": "Healthcare Provider"
      },
      {
        "system": "http://va.gov/fhir/organization-type",
        "code": "cboc",
        "display": "Community Based Outpatient Clinic"
      }
    ],
    "text": "Healthcare Provider"
  },
  "name": "Virginia Beach CBOC",
  "telecom": [
    {
      "system": "phone",
      "value": "757-722-9961",
      "use": "work"
    }
  ],
  "address": [
    {
      "use": "work",
      "type": "both",
      "line": [
        "244 Clearfield Ave"
      ],
      "city": "Virginia Beach",
      "postalCode": "23462",
      "state": "VA",
      "country": "USA"
    }
  ],
  "partOf": {
    "reference": "Organization/va-org-visn6",
    "display": "VA Mid-Atlantic Health Care Network"
  }
}