{
  "resourceType": "Goal",
  "id": "va-goal-dan-a1c",
  "meta": {
    "profile": [
      "http://hl7.org/fhir/StructureDefinition/Goal"
    ]
  },
  "text": {
    "status": "generated",
    "div": "<div xmlns=\"http://www.w3.org/1999/xhtml\"><div>Goal: Hemoglobin A1c &lt; 7.0</div></div>"
  },
  "status": "in-progress",
  "priority": {
    "coding": [
      {
        "system": "http://hl7.org/fhir/goal-priority",
        "code": "high",
        "display": "high"
      }
    ],
    "text": "high"
  },
  "description": {
    "text": "Hemoglobin A1c < 7.0"
  },
  "subject": {
    "reference": "Patient/va-pat-dan",
    "display": "Dan"
  },
  "startDate": "2014-11-30",
  "target": {
    "measure": {
      "coding": [
        {
          "system": "http://loinc.org",
          "code": "4548-4",
          "display": "Hemoglobin A1c total in Blood"
        }
      ],
      "text": "Hemoglobin A1c total in Blood"
    },
    "detailQuantity": {
      "value": "7.0",
      "comparator": "<",
      "unit": "%",
      "system": "http://unitsofmeasure.org/",
      "code": "%"
    }
  },
  "expressedBy": {
    "reference": "Practitioner/va-prac-visn6-francis",
    "display": "Dr. Francis, MD"
  },
  "addresses": [
    {
      "reference": "Condition/va-cond-dan-dm",
      "display": "Type 2 diabetes mellitus"
    }
  ],
  "note": [
    {
      "text": "Regularly monitor A1C levels toward overall goal of 6.0."
    }
  ]
}